{
  "point_id": "017",
  "subject_id": "high_itpmp",
  "chapter_id": "ch_16",
  "section_id": "sec_01",
  "title": "立项管理文件                  1",
  "card_type": "concept",
  "difficulty": 2,
  "estimated_read_seconds": 30,
  "has_key_content": true,
  "is_free": true,
  "sort_no": 17,
  "tags": [
    "采购管理",
    "采购管理"
  ],
  "key_points": [
    "立项管理文件                  1. 专家判断                     1.采购管理计划"
  ],
  "mnemonics": [],
  "common_mistakes": [],
  "review_status": "ai_draft",
  "content_file": "ch_16_sec_01_017.md",
  "content_md_path": "subjects/high_itpmp/chapters/ch_16/cards/ch_16_sec_01_017.md",
  "source_refs": [
    {
      "source": "2026新版高项三色笔记",
      "location": "ch_16"
    }
  ]
}