{
  "point_id": "017",
  "subject_id": "high_itpmp",
  "chapter_id": "ch_22",
  "section_id": "sec_02",
  "title": "绩效计划包",
  "card_type": "definition",
  "difficulty": 2,
  "estimated_read_seconds": 45,
  "has_key_content": true,
  "is_free": true,
  "sort_no": 17,
  "tags": [
    "组织通用治理",
    "绩效考核"
  ],
  "key_points": [
    "> 。 绩效标准对特定的职务工作而音，是要求员工在工作中应达到的各种基本要求。绩效标准反映了职务本",
    ">绩效目标是在绩效标准的基础上，考虑员工现有的绩效水平确定的，体现卫管理者对员工的具体要求。"
  ],
  "mnemonics": [],
  "common_mistakes": [],
  "review_status": "ai_draft",
  "content_file": "ch_22_sec_02_017.md",
  "content_md_path": "subjects/high_itpmp/chapters/ch_22/cards/ch_22_sec_02_017.md",
  "source_refs": [
    {
      "source": "2026新版高项三色笔记",
      "location": "ch_22"
    }
  ]
}