{
  "point_id": "038",
  "subject_id": "high_itpmp",
  "chapter_id": "ch_22",
  "section_id": "sec_03",
  "title": "转型组织的建立",
  "card_type": "concept",
  "difficulty": 2,
  "estimated_read_seconds": 43,
  "has_key_content": true,
  "is_free": true,
  "sort_no": 38,
  "tags": [
    "组织通用治理",
    "转型提升级"
  ],
  "key_points": [
    "转型组织的建立:数字化转型组织架构及工作机制的建议可分为个层次",
    "工问咯王原尿能划 组朋数字化转型丰与原巡的核心是币定歼字化罗丈珊划， 开设"
  ],
  "mnemonics": [],
  "common_mistakes": [],
  "review_status": "ai_draft",
  "content_file": "ch_22_sec_03_038.md",
  "content_md_path": "subjects/high_itpmp/chapters/ch_22/cards/ch_22_sec_03_038.md",
  "source_refs": [
    {
      "source": "2026新版高项三色笔记",
      "location": "ch_22"
    }
  ]
}