{
  "point_id": "027",
  "subject_id": "high_itpmp",
  "chapter_id": "ch_12",
  "section_id": "sec_02",
  "title": "检查",
  "card_type": "concept",
  "difficulty": 2,
  "estimated_read_seconds": 147,
  "has_key_content": true,
  "is_free": false,
  "sort_no": 27,
  "content_file": "ch_12_sec_02_027.md",
  "tags": [
    "质量管理",
    "管理过程",
    "检查"
  ],
  "key_points": "1. 4.检查：是指检验工作产品，以确定是否符合书面标准。\n2. 测试是一种有组织的、结构化的调查，旨在根据项目需求提供有关被测产品或服务质量的客观信息。\n3. 测试的目的是找出产品或服务中存在的错误、缺陷、漏洞或其他不合规问题。用于评估各项需求的",
  "mnemonics": "",
  "prerequisite_point_ids": [
    "026"
  ],
  "related_point_ids": [],
  "related_question_ids": [],
  "source": "2026新版高项三色笔记（信息系统项目管理师）",
  "source_type": "exam_note",
  "source_refs": [
    {
      "source_id": "pdf_2026_tricolor_high",
      "page_label": "OCR自动定位待复核"
    }
  ],
  "author": "Codex OCR 批量整理",
  "reviewer": "待人工复核",
  "review_status": "ai_draft",
  "created_at": "2026-05-11T00:00:00+08:00",
  "updated_at": "2026-05-11T00:00:00+08:00",
  "version": 1,
  "schema_version": 2
}
