{
  "point_id": "022",
  "subject_id": "high_itpmp",
  "chapter_id": "ch_02",
  "section_id": "sec_03",
  "title": "UEBA 用户和实体行为分析",
  "card_type": "definition",
  "difficulty": 3,
  "estimated_read_seconds": 60,
  "has_key_content": false,
  "is_free": true,
  "sort_no": 22,
  "tags": [
    "信息安全",
    "UEBA",
    "行为分析"
  ],
  "key_points": "UEBA 以**用户和实体**为对象，结合**规则、统计、机器学习、大数据**，识别标准画像或行为基线之外的异常活动。",
  "mnemonics": "",
  "common_mistakes": [],
  "review_status": "ai_draft",
  "content_file": "ch_02_sec_03_022.md",
  "content_md_path": "subjects/high_itpmp/chapters/ch_02/cards/ch_02_sec_03_022.md",
  "source_refs": [
    {
      "source_id": "pdf_2026_tricolor_high",
      "page_label": "22"
    }
  ]
}
