{
  "point_id": "039",
  "subject_id": "high_itpmp",
  "chapter_id": "ch_14",
  "section_id": "sec_01",
  "title": "人际关系与团队技能;与项目团队展开讨论和对话",
  "card_type": "concept",
  "difficulty": 2,
  "estimated_read_seconds": 30,
  "has_key_content": true,
  "is_free": true,
  "sort_no": 39,
  "tags": [
    "沟通管理",
    "沟通管理"
  ],
  "key_points": [
    "人际关系与团队技能;与项目团队展开讨论和对话，有助于确定最合适的方法，用于更新和沟通项"
  ],
  "mnemonics": [],
  "common_mistakes": [],
  "review_status": "ai_draft",
  "content_file": "ch_14_sec_01_039.md",
  "content_md_path": "subjects/high_itpmp/chapters/ch_14/cards/ch_14_sec_01_039.md",
  "source_refs": [
    {
      "source": "2026新版高项三色笔记",
      "location": "ch_14"
    }
  ]
}