{
  "point_id": "041",
  "subject_id": "high_itpmp",
  "chapter_id": "ch_20",
  "section_id": "sec_05",
  "title": "理级所有第3级实践的意图和价值都能够达成",
  "card_type": "concept",
  "difficulty": 3,
  "estimated_read_seconds": 65,
  "has_key_content": true,
  "is_free": true,
  "sort_no": 41,
  "content_file": "ch_20_sec_05_041.md",
  "content_md_path": "subjects/high_itpmp/chapters/ch_20/cards/ch_20_sec_05_041.md",
  "tags": [
    "高级项目管理",
    "项目管理实践模型",
    "CMM15个成熟度级别分别如下",
    "理级所有第3级实践的意图和价值都",
    "理级所有第3级实践的意图和价值都"
  ],
  "key_points": "- 理级所有第3级实践的意图和价值都能够达成。另外，组织的管理实现了量化，实现了可预测。通过**统计或其他量化技术来实现过程性能的稳**定性监控和复合型监控，实现管理的精细化，降低项目在过程能力和质量上的波动。组织能够通过**历史数据使用统计和其他量化技术**来监测，完善或预测关\n- 键过程领域从而实现组织或项目的质量与过程性\n- 能目标",
  "mnemonics": "",
  "warnings": "已做 OCR 噪声、标题、重点标注和卡片粒度修复；上线前仍建议抽样核对原 PDF。",
  "prerequisite_point_ids": [
    "040"
  ],
  "related_point_ids": [],
  "related_question_ids": [],
  "source": "2026新版高项三色笔记（信息系统项目管理师）",
  "source_type": "exam_note",
  "source_refs": [
    {
      "source_id": "pdf_2026_tricolor_high",
      "page_label": "210"
    }
  ],
  "author": "Codex color OCR 批量整理",
  "reviewer": "待人工复核",
  "review_status": "ai_draft",
  "created_at": "2026-05-13T00:00:00+08:00",
  "updated_at": "2026-05-13T00:00:00+08:00",
  "version": 2,
  "schema_version": 2
}
