{
  "point_id": "018",
  "subject_id": "high_itpmp",
  "chapter_id": "ch_22",
  "section_id": "sec_08",
  "title": "战略转型提升级是指组织为适应外部经济与社会环",
  "card_type": "concept",
  "difficulty": 2,
  "estimated_read_seconds": 233,
  "has_key_content": true,
  "is_free": true,
  "sort_no": 18,
  "content_file": "ch_22_sec_08_018.md",
  "tags": [
    "组织通用治理",
    "战略转型提升级",
    "战略转型提升级是指组织为适应外部"
  ],
  "key_points": "1. 1、战略转型提升级是指组织为适应外部经济与社会环境以及内部环境的变化，对组织的长期发展方向、\n2. 运行模式、组织战略、组织方式、资源配置方式、组织文化等进行全方位提升级变革。转型提升级是组织提\n3. 组织转型提升级首先要解决的是战略选择问题。在战略提升级过程中，首先要对组织",
  "mnemonics": "",
  "prerequisite_point_ids": [
    "017"
  ],
  "related_point_ids": [],
  "related_question_ids": [],
  "source": "2026新版高项三色笔记（信息系统项目管理师）",
  "source_type": "exam_note",
  "source_refs": [
    {
      "source_id": "pdf_2026_tricolor_high",
      "page_label": "OCR自动定位待复核"
    }
  ],
  "author": "Codex OCR 批量整理",
  "reviewer": "待人工复核",
  "review_status": "ai_draft",
  "created_at": "2026-05-11T00:00:00+08:00",
  "updated_at": "2026-05-11T00:00:00+08:00",
  "version": 1,
  "schema_version": 2,
  "warnings": "本卡片由 OCR 文本自动整理，`review_status` 为 `ai_draft`，上线前需要人工核对原文、表格和红色重点。"
}
