{
  "point_id": "096",
  "subject_id": "high_itpmp",
  "chapter_id": "ch_05",
  "section_id": "sec_04",
  "title": "代表性的软件构件标准",
  "card_type": "concept",
  "difficulty": 2,
  "estimated_read_seconds": 42,
  "has_key_content": true,
  "is_free": true,
  "sort_no": 96,
  "tags": [
    "信息系统工程",
    "安全工程"
  ],
  "key_points": [
    "信息安全三维空间:X抽是“安全机制”、Y 轴是“0SI 网络参考模型”、2Z 轴是“安全服务”"
  ],
  "mnemonics": [],
  "common_mistakes": [],
  "review_status": "ai_draft",
  "content_file": "ch_05_sec_04_096.md",
  "content_md_path": "subjects/high_itpmp/chapters/ch_05/cards/ch_05_sec_04_096.md",
  "source_refs": [
    {
      "source": "2026新版高项三色笔记",
      "location": "ch_05"
    }
  ]
}